{
    "keybaseIdentity": "F87ADDB700C0CC94",
    "name": "Lavender.Five Nodes ?",
    "website": "https://www.lavenderfive.com/",
    "twitter": null,
    "telegram": null,
    "discord": null,
    "email": null,
    "supportRelayerBy": "delegate to validator",
    "chainsRelayed": [
        {
            "ticker": "ATOM",
            "relayerAddress": null
        },
        {
            "ticker": "EVMOS",
            "relayerAddress": null
        },
        {
            "ticker": "JUNO",
            "relayerAddress": null
        },
        {
            "ticker": "KUJI",
            "relayerAddress": null
        },
        {
            "ticker": "OSMO",
            "relayerAddress": null
        }
    ]
}